flask_does_redis/__init__.py
flask_does_redis-0.3.15.dist-info/LICENSE
flask_does_redis-0.3.15.dist-info/METADATA
flask_does_redis-0.3.15.dist-info/WHEEL
flask_does_redis-0.3.15.dist-info/top_level.txt
flask_does_redis-0.3.15.dist-info/RECORD
