Metadata-Version: 2.1
Name: flask-does-redis
Version: 0.3.15
Summary: Flask extension to easily reuse redis connection pools
License: MIT
Keywords: api,auth
Classifier: Development Status :: 5 - Production/Stable
Classifier: Environment :: Web Environment
Classifier: Framework :: Flask
Classifier: License :: OSI Approved :: MIT License
License-File: LICENSE
Requires-Dist: flask
Requires-Dist: redis
Requires-Dist: importlib-metadata ; python_version < "3.8"
